CHANGES.txt
MANIFEST.in
README.txt
setup.py
rstctl/__init__.py
rstctl/blog.tmpl
rstctl/module.tmpl
rstctl/pdf.py
rstctl/rst_directive.py
rstctl/serve.py
rstctl/sphinx.py
rstctl/template.py
rstctl/utils.py
rstctl.egg-info/PKG-INFO
rstctl.egg-info/SOURCES.txt
rstctl.egg-info/dependency_links.txt
rstctl.egg-info/entry_points.txt
rstctl.egg-info/not-zip-safe
rstctl.egg-info/requires.txt
rstctl.egg-info/top_level.txt