Metadata-Version: 1.0
Name: rstctl
Version: 0.4
Summary: reST utils
Home-page: http://www.gawel.org
Author: Gael Pasgrimaud
Author-email: gael@gawel.org
License: GPL
Keywords: reST
Platform: UNKNOWN
Classifier: Environment :: Console
Classifier: License :: OSI Approved :: GNU General Public License (GPL)
Classifier: Operating System :: OS Independent
Classifier: Topic :: Utilities
